carmen_cloud_client/__init__.py
carmen_cloud_client/errors.py
carmen_cloud_client/models.py
carmen_cloud_client/utils.py
carmen_cloud_client/storage_and_hook/__init__.py
carmen_cloud_client/storage_and_hook/api_storage_status_request.py
carmen_cloud_client/storage_and_hook/client.py
carmen_cloud_client/storage_and_hook/create_hook_request.py
carmen_cloud_client/storage_and_hook/events_response.py
carmen_cloud_client/storage_and_hook/hook.py
carmen_cloud_client/storage_and_hook/ok_response.py
carmen_cloud_client/storage_and_hook/options.py
carmen_cloud_client/storage_and_hook/storage_status_response.py
carmen_cloud_client/storage_and_hook/update_hook_request.py
carmen_cloud_client/test/__init__.py
carmen_cloud_client/test/utils.py
carmen_cloud_client/test/storage_and_hook/__init__.py
carmen_cloud_client/test/storage_and_hook/test_client.py
carmen_cloud_client/test/transport/__init__.py
carmen_cloud_client/test/transport/accr_usa01.jpg
carmen_cloud_client/test/transport/accr_usa02.jpg
carmen_cloud_client/test/transport/accr_usa03.jpg
carmen_cloud_client/test/transport/accr_usa20.jpg
carmen_cloud_client/test/transport/bra01.jpg
carmen_cloud_client/test/transport/bra02.jpg
carmen_cloud_client/test/transport/bra03.jpg
carmen_cloud_client/test/transport/bra20.jpg
carmen_cloud_client/test/transport/chassis01.jpg
carmen_cloud_client/test/transport/chassis02.jpg
carmen_cloud_client/test/transport/chassis03.jpg
carmen_cloud_client/test/transport/chassis20.jpg
carmen_cloud_client/test/transport/ilu01.jpg
carmen_cloud_client/test/transport/ilu02.jpg
carmen_cloud_client/test/transport/ilu03.jpg
carmen_cloud_client/test/transport/ilu20.jpg
carmen_cloud_client/test/transport/iso01.jpg
carmen_cloud_client/test/transport/iso02.jpg
carmen_cloud_client/test/transport/iso20.jpg
carmen_cloud_client/test/transport/test_client.py
carmen_cloud_client/test/transport/uic01.jpg
carmen_cloud_client/test/transport/uic02.jpg
carmen_cloud_client/test/transport/uic03.jpg
carmen_cloud_client-1.3.1.dist-info/METADATA
carmen_cloud_client-1.3.1.dist-info/WHEEL
carmen_cloud_client-1.3.1.dist-info/licenses/LICENSE
carmen_cloud_client-1.3.1.dist-info/RECORD
