Metadata-Version: 2.4
Name: carmen_cloud_client
Version: 1.3.1
Summary: Python client for Carmen Cloud by Adaptive Recognition. Efficiently read license plates, recognize vehicle details, and process container, railway wagon, and US DOT codes.
Project-URL: Homepage, https://github.com/adaptiverecognition/python-carmen-cloud-client
Project-URL: Bug Tracker, https://github.com/adaptiverecognition/python-carmen-cloud-client/issues
Author-email: Botond BALÁZS <botond.balazs@arip.hu>
License-File: LICENSE
Classifier: License :: OSI Approved :: MIT License
Classifier: Operating System :: OS Independent
Classifier: Programming Language :: Python :: 3
Requires-Python: >=3.7
Requires-Dist: pydantic>=1.10.9
Requires-Dist: requests-toolbelt>=1.0.0
Requires-Dist: requests>=2.31.0
Requires-Dist: urllib3>=2.0.3
